pyefa/__init__.py
pyefa/classes.py
pyefa/efa.py
pyefa/exceptions.py
pyefa/networks.py
pyefa/tools.py
pyefa/triprequest.py
pyefa3-0.2.3.dist-info/LICENSE
pyefa3-0.2.3.dist-info/METADATA
pyefa3-0.2.3.dist-info/WHEEL
pyefa3-0.2.3.dist-info/top_level.txt
pyefa3-0.2.3.dist-info/RECORD
